python_final_project/__init__.py
python_final_project/ascii.py
python_final_project/cli.py
python_final_project-0.1.0.dist-info/entry_points.txt
python_final_project-0.1.0.dist-info/WHEEL
python_final_project-0.1.0.dist-info/METADATA
python_final_project-0.1.0.dist-info/RECORD
