Metadata-Version: 2.1
Name: python-final-project
Version: 0.1.0
Summary: 
Author: Will Lane
Author-email: williamlane923@gmail.com
Requires-Python: >=3.9,<4.0
Classifier: Programming Language :: Python :: 3
Classifier: Programming Language :: Python :: 3.9
Requires-Dist: Pillow (>=8.2.0,<9.0.0)
Requires-Dist: fire (>=0.4.0,<0.5.0)
